RobotOil/Smart_Browser.py
RobotOil/Smart_Keywords.py
RobotOil/Utility_Webdriver_Setup.py
RobotOil/__init__.py
robotframework_RobotOil-1.0.0.dist-info/LICENCE
robotframework_RobotOil-1.0.0.dist-info/METADATA
robotframework_RobotOil-1.0.0.dist-info/WHEEL
robotframework_RobotOil-1.0.0.dist-info/top_level.txt
robotframework_RobotOil-1.0.0.dist-info/RECORD
