Metadata-Version: 2.1
Name: robotframework-RobotOil
Version: 1.0.0
Summary: Quality of life upgrades for common-use Keywords in the Robot Framework and SeleniumLibrary packages.
Home-page: https://github.com/Worakow1138/RobotOil
Author: Christopher Jones
Author-email: christopher.jones1138@gmail.com
Classifier: Programming Language :: Python :: 3
Classifier: License :: OSI Approved :: MIT License
Classifier: Operating System :: OS Independent
Requires-Python: >=3.6
License-File: LICENCE
